colorpick/__init__.py
colorpick/py.typed
colorpick-2.4.3.dist-info/LICENSE
colorpick-2.4.3.dist-info/METADATA
colorpick-2.4.3.dist-info/WHEEL
colorpick-2.4.3.dist-info/RECORD
