Metadata-Version: 2.1
Name: colorpick
Version: 2.4.3
Summary: Create curses-based interactive selection list in the terminal. Now with color!
Home-page: https://github.com/DJStompZone/colorpick
License: MIT
Keywords: terminal,gui,curses,colorama
Author: wong2
Author-email: wonderfuly@gmail.com
Requires-Python: >=3.7
Classifier: License :: OSI Approved :: MIT License
Classifier: Programming Language :: Python :: 3
Classifier: Programming Language :: Python :: 3.7
Classifier: Programming Language :: Python :: 3.8
Classifier: Programming Language :: Python :: 3.9
Classifier: Programming Language :: Python :: 3.10
Classifier: Programming Language :: Python :: 3.11
Classifier: Programming Language :: Python :: 3.12
Requires-Dist: colorama (>=0.4.6)
Requires-Dist: windows-curses (>=2.2.0,<3.0.0) ; sys_platform == "win32"
Project-URL: Repository, https://github.com/DJStompZone/colorpick
